dstk/__init__.py
dstk/method_index.py
dstk/utils.py
dstk/adaptors/__init__.py
dstk/adaptors/adaptors.py
dstk/adaptors/typeguards.py
dstk/hooks/__init__.py
dstk/hooks/hook_tools.py
dstk/hooks/type_conversion.py
dstk/lib_types/__init__.py
dstk/lib_types/dstk_types.py
dstk/lib_types/fasttext_types.py
dstk/lib_types/gensim_types.py
dstk/lib_types/numpy_types.py
dstk/lib_types/pandas_types.py
dstk/lib_types/plotly_types.py
dstk/lib_types/sklearn_types.py
dstk/lib_types/spacy_types.py
dstk/models/__init__.py
dstk/models/model_tools.py
dstk/models/models.py
dstk/modules/__init__.py
dstk/modules/count_models.py
dstk/modules/geometric_distance.py
dstk/modules/ngrams.py
dstk/modules/predict_models.py
dstk/modules/text_matrix_builder.py
dstk/modules/text_processor.py
dstk/modules/tokenizer.py
dstk/modules/weight_matrix.py
dstk/modules/data_visualization/__init__.py
dstk/modules/data_visualization/clustering.py
dstk/modules/data_visualization/embeddings.py
dstk/templates/__init__.py
dstk/templates/rules.py
dstk/templates/templates.py
dstk/workflows/__init__.py
dstk/workflows/stage_workflows.py
dstk/workflows/workflow_tools.py
dstklib-2.1.0.dist-info/LICENSE
dstklib-2.1.0.dist-info/METADATA
dstklib-2.1.0.dist-info/WHEEL
dstklib-2.1.0.dist-info/top_level.txt
dstklib-2.1.0.dist-info/RECORD
