Metadata-Version: 2.1
Name: dstklib
Version: 2.1.0
Requires-Python: <3.13
License-File: LICENSE
Requires-Dist: spacy
Requires-Dist: plotly
Requires-Dist: scikit-learn
Requires-Dist: pandas
Requires-Dist: numpy
Requires-Dist: gensim
Requires-Dist: fasttext
Requires-Dist: kneed
Requires-Dist: umap-learn
Requires-Dist: nltk
